serper_mcp_server/__init__.py
serper_mcp_server/core.py
serper_mcp_server/enums.py
serper_mcp_server/schemas.py
serper_mcp_server/server.py
serper_mcp_server-0.0.10.dist-info/METADATA
serper_mcp_server-0.0.10.dist-info/WHEEL
serper_mcp_server-0.0.10.dist-info/entry_points.txt
serper_mcp_server-0.0.10.dist-info/top_level.txt
serper_mcp_server-0.0.10.dist-info/RECORD
